opentelemetry/exporter/zipkin/proto/http/__init__.py
opentelemetry/exporter/zipkin/proto/http/py.typed
opentelemetry/exporter/zipkin/proto/http/v2/__init__.py
opentelemetry/exporter/zipkin/proto/http/v2/gen/__init__.py
opentelemetry/exporter/zipkin/proto/http/v2/gen/zipkin_pb2.py
opentelemetry/exporter/zipkin/proto/http/v2/gen/zipkin_pb2.pyi
opentelemetry/exporter/zipkin/proto/http/version/__init__.py
opentelemetry_exporter_zipkin_proto_http-1.39.1.dist-info/METADATA
opentelemetry_exporter_zipkin_proto_http-1.39.1.dist-info/WHEEL
opentelemetry_exporter_zipkin_proto_http-1.39.1.dist-info/entry_points.txt
opentelemetry_exporter_zipkin_proto_http-1.39.1.dist-info/licenses/LICENSE
opentelemetry_exporter_zipkin_proto_http-1.39.1.dist-info/RECORD
