Metadata-Version: 2.4
Name: opentelemetry-exporter-zipkin-proto-http
Version: 1.39.1
Summary: Zipkin Span Protobuf Exporter for OpenTelemetry
Project-URL: Homepage, https://github.com/open-telemetry/opentelemetry-python/tree/main/exporter/opentelemetry-exporter-zipkin-proto-http
Project-URL: Repository, https://github.com/open-telemetry/opentelemetry-python
Author-email: OpenTelemetry Authors <cncf-opentelemetry-contributors@lists.cncf.io>
License-Expression: Apache-2.0
License-File: LICENSE
Classifier: Development Status :: 5 - Production/Stable
Classifier: Framework :: OpenTelemetry
Classifier: Framework :: OpenTelemetry :: Exporters
Classifier: Intended Audience :: Developers
Classifier: Programming Language :: Python
Classifier: Programming Language :: Python :: 3
Classifier: Programming Language :: Python :: 3.9
Classifier: Programming Language :: Python :: 3.10
Classifier: Programming Language :: Python :: 3.11
Classifier: Programming Language :: Python :: 3.12
Classifier: Programming Language :: Python :: 3.13
Classifier: Typing :: Typed
Requires-Python: >=3.9
Requires-Dist: opentelemetry-api~=1.3
Requires-Dist: opentelemetry-exporter-zipkin-json==1.39.1
Requires-Dist: opentelemetry-sdk~=1.11
Requires-Dist: protobuf~=3.12
Requires-Dist: requests~=2.7
